keras_genetic/__init__.py
keras_genetic/breeder/__init__.py
keras_genetic/breeder/breeder.py
keras_genetic/breeder/completely_random_breeder.py
keras_genetic/breeder/mutation_breeder.py
keras_genetic/breeder/n_parent_mutation_breeder.py
keras_genetic/callbacks/__init__.py
keras_genetic/callbacks/callback.py
keras_genetic/callbacks/early_stopping.py
keras_genetic/callbacks/prog_bar_logger.py
keras_genetic/core/__init__.py
keras_genetic/core/individual.py
keras_genetic/initializers/__init__.py
keras_genetic/initializers/initializer.py
keras_genetic/initializers/random_normal.py
keras_genetic/search/__init__.py
keras_genetic/search/result.py
keras_genetic/search/search.py
keras_genetic-0.1.0.dist-info/METADATA
keras_genetic-0.1.0.dist-info/WHEEL
keras_genetic-0.1.0.dist-info/top_level.txt
keras_genetic-0.1.0.dist-info/RECORD
