Metadata-Version: 2.1
Name: keras-genetic
Version: 0.1.0
Summary: Train keras models with genetic algorithms.
Home-page: https://github.com/lukewood/keras-genetic
Author: Luke Wood
Author-email: lukewoodcs@gmail.com
License: Apache License 2.0
Platform: UNKNOWN
Classifier: Programming Language :: Python
Classifier: Programming Language :: Python :: 3.7
Classifier: Operating System :: Unix
Classifier: Operating System :: Microsoft :: Windows
Classifier: Operating System :: MacOS
Classifier: Topic :: Software Development
Provides-Extra: examples
Requires-Dist: gym ; extra == 'examples'
Requires-Dist: pygame ; extra == 'examples'
Provides-Extra: tests
Requires-Dist: flake8 ; extra == 'tests'
Requires-Dist: isort ; extra == 'tests'
Requires-Dist: black ; extra == 'tests'
Requires-Dist: pytest ; extra == 'tests'
